CHANGELOG.md
LICENSE.txt
MANIFEST.in
README.md
requirements.txt
setup.py
react/__init__.py
react/bundle.py
react/conf.py
react/exceptions.py
react/models.py
react/render.py
react/templates.py
react.egg-info/PKG-INFO
react.egg-info/SOURCES.txt
react.egg-info/dependency_links.txt
react.egg-info/requires.txt
react.egg-info/top_level.txt