Metadata-Version: 1.0
Name: react
Version: 0.12.0
Summary: Server-side rendering, client-side mounting, JSX translation, and component bundling
Home-page: https://github.com/markfinger/python-react
Author: Mark Finger
Author-email: markfinger@gmail.com
License: UNKNOWN
Platform: UNKNOWN
